{
  "topic": "TOEIC Day 91 - Corporate Governance",
  "words": [
    {
      "word": "board oversight",
      "partOfSpeech": "n. phr.",
      "ipa": "/bɔːd ˈəʊvəsaɪt/",
      "meaning": "giám sát của hội đồng quản trị"
    },
    {
      "word": "fiduciary duty",
      "partOfSpeech": "n. phr.",
      "ipa": "/fɪˈdjuːʃəri ˈdjuːti/",
      "meaning": "nghĩa vụ ủy thác"
    },
    {
      "word": "audit committee",
      "partOfSpeech": "n. phr.",
      "ipa": "/ˈɔːdɪt kəˈmɪti/",
      "meaning": "ủy ban kiểm toán"
    },
    {
      "word": "governance charter",
      "partOfSpeech": "n. phr.",
      "ipa": "/ˈɡʌvənəns ˈtʃɑːtə/",
      "meaning": "điều lệ quản trị"
    },
    {
      "word": "risk appetite",
      "partOfSpeech": "n. phr.",
      "ipa": "/rɪsk ˈæpɪtaɪt/",
      "meaning": "khẩu vị rủi ro"
    },
    {
      "word": "ethics hotline",
      "partOfSpeech": "n. phr.",
      "ipa": "/ˈeθɪks ˈhɒtlaɪn/",
      "meaning": "đường dây tố giác đạo đức"
    },
    {
      "word": "proxy statement",
      "partOfSpeech": "n. phr.",
      "ipa": "/ˈprɒksi ˈsteɪtmənt/",
      "meaning": "tờ ủy quyền biểu quyết"
    },
    {
      "word": "majority voting",
      "partOfSpeech": "n. phr.",
      "ipa": "/məˈdʒɒrɪti ˈvəʊtɪŋ/",
      "meaning": "bỏ phiếu đa số"
    },
    {
      "word": "independent director",
      "partOfSpeech": "n. phr.",
      "ipa": "/ˌɪndɪˈpendənt dɪˈrektə/",
      "meaning": "thành viên HĐQT độc lập"
    },
    {
      "word": "conflict of interest",
      "partOfSpeech": "n. phr.",
      "ipa": "/ˈkɒnflɪkt əv ˈɪntrəst/",
      "meaning": "xung đột lợi ích"
    },
    {
      "word": "whistleblower protection",
      "partOfSpeech": "n. phr.",
      "ipa": "/ˈwɪslˌbləʊə prəˈtekʃən/",
      "meaning": "bảo vệ người tố giác"
    },
    {
      "word": "internal control",
      "partOfSpeech": "n.",
      "ipa": "/ɪnˈtɜːnl kənˈtrəʊl/",
      "meaning": "kiểm soát nội bộ"
    },
    {
      "word": "compliance calendar",
      "partOfSpeech": "n. phr.",
      "ipa": "/kəmˈplaɪəns ˈkælɪndə/",
      "meaning": "lịch tuân thủ"
    },
    {
      "word": "succession planning",
      "partOfSpeech": "n. phr.",
      "ipa": "/səkˈseʃən ˈplænɪŋ/",
      "meaning": "kế hoạch kế nhiệm"
    },
    {
      "word": "shareholder activism",
      "partOfSpeech": "n. phr.",
      "ipa": "/ˈʃeəˌhəʊldə ˈæktɪvɪzəm/",
      "meaning": "hoạt động của cổ đông"
    },
    {
      "word": "ESG disclosure",
      "partOfSpeech": "n. phr.",
      "ipa": "/iː ɛs dʒiː dɪsˈkləʊʒə/",
      "meaning": "công bố ESG"
    },
    {
      "word": "chairperson",
      "partOfSpeech": "n.",
      "ipa": "/ˈtʃeəˌpɜːsən/",
      "meaning": "chủ tịch"
    },
    {
      "word": "board tenure",
      "partOfSpeech": "n. phr.",
      "ipa": "/bɔːd ˈtenjə/",
      "meaning": "nhiệm kỳ hội đồng"
    },
    {
      "word": "strategic mandate",
      "partOfSpeech": "n. phr.",
      "ipa": "/strəˈtiːdʒɪk ˈmændeɪt/",
      "meaning": "ủy nhiệm chiến lược"
    },
    {
      "word": "non-executive director",
      "partOfSpeech": "n. phr.",
      "ipa": "/nɒn ɪɡˈzekjʊtɪv dɪˈrektə/",
      "meaning": "thành viên không điều hành"
    },
    {
      "word": "board diversity",
      "partOfSpeech": "n. phr.",
      "ipa": "/bɔːd daɪˈvɜːsɪti/",
      "meaning": "đa dạng hội đồng"
    },
    {
      "word": "governance roadmap",
      "partOfSpeech": "n. phr.",
      "ipa": "/ˈɡʌvənəns ˈrəʊdmæp/",
      "meaning": "lộ trình quản trị"
    },
    {
      "word": "code of conduct",
      "partOfSpeech": "n. phr.",
      "ipa": "/kəʊd əv ˈkɒndʌkt/",
      "meaning": "bộ quy tắc ứng xử"
    },
    {
      "word": "stakeholder dialogue",
      "partOfSpeech": "n. phr.",
      "ipa": "/ˈsteɪkˌhəʊldə ˈdaɪəlɒɡ/",
      "meaning": "đối thoại với bên liên quan"
    },
    {
      "word": "annual general meeting",
      "partOfSpeech": "n. phr.",
      "ipa": "/ˈænjuəl ˈdʒenrəl ˈmiːtɪŋ/",
      "meaning": "đại hội cổ đông thường niên"
    }
  ]
}
